kickcat.cpython-310-x86_64-linux-gnu.so
kickcat-2.4rc0.dist-info/METADATA
kickcat-2.4rc0.dist-info/WHEEL
kickcat-2.4rc0.dist-info/RECORD
kickcat-2.4rc0.dist-info/licenses/LICENSE
