Metadata-Version: 2.2
Name: kickcat
Version: 2.4rc0
Summary: Thin EtherCAT stack designed to be embedded in a more complex software.
Maintainer-Email: Philippe Leduc <ledphilippe@gmail.com>
License: CeCILL-C
